[{"date":"Wed, 18 Oct 2017 07:08:04 GMT","sloc":64,"lloc":40,"functions":8,"deliveredBugs":0.5545555342054101,"maintainability":124.3202814816916,"lintErrors":5,"difficulty":15.9375},{"date":"Wed, 18 Oct 2017 07:30:41 GMT","sloc":64,"lloc":40,"functions":8,"deliveredBugs":0.5545555342054101,"maintainability":124.3202814816916,"lintErrors":5,"difficulty":15.9375},{"date":"Wed, 18 Oct 2017 07:31:20 GMT","sloc":64,"lloc":40,"functions":8,"deliveredBugs":0.5545555342054101,"maintainability":124.3202814816916,"lintErrors":5,"difficulty":15.9375}]